AUTHORS.md
CHANGELOG.md
MANIFEST.in
README.md
setup.py
django_zms_news.egg-info/PKG-INFO
django_zms_news.egg-info/SOURCES.txt
django_zms_news.egg-info/dependency_links.txt
django_zms_news.egg-info/requires.txt
django_zms_news.egg-info/top_level.txt
news/__init__.py
news/admin.py
news/models.py
news/tests.py
news/urls.py
news/views.py
news/templates/news/new_detail.html
news/templates/news/news_index.html
news/templates/news/news_list.html